beeseeder/__init__.py
beeseeder/admin.py
beeseeder/apps.py
beeseeder/bee_logger.py
beeseeder/data_generator.py
beeseeder/models.py
beeseeder/services.py
beeseeder/tests.py
beeseeder/utils.py
beeseeder/views.py
beeseeder/management/__init__.py
beeseeder/management/commands/__init__.py
beeseeder/management/commands/beeseed.py
beeseeder/migrations/__init__.py
django_beeseeder-0.1.1.dist-info/METADATA
django_beeseeder-0.1.1.dist-info/WHEEL
django_beeseeder-0.1.1.dist-info/top_level.txt
django_beeseeder-0.1.1.dist-info/RECORD
